demo/demo.py
qq_doc/__init__.py
qq_doc/auth_api.py
qq_doc/base.py
qq_doc/file_mgr_api.py
qq_doc-0.1.0.dev3.dist-info/METADATA
qq_doc-0.1.0.dev3.dist-info/WHEEL
qq_doc-0.1.0.dev3.dist-info/top_level.txt
qq_doc-0.1.0.dev3.dist-info/RECORD
