Metadata-Version: 2.1
Name: qq_doc
Version: 0.1.0.dev3
Summary: QQ Doc is a simple document management system.
Author-email: Pan Zhongxian <panzhongxian0532@gmail.com>
License: MIT
Project-URL: Homepage, https://github.com/easy-wx/qq-doc
Project-URL: Issues, https://github.com/easy-wx/qq-doc/issues
Classifier: Programming Language :: Python :: 3
Classifier: License :: OSI Approved :: MIT License
Classifier: Operating System :: OS Independent
Requires-Python: >=3.8
